MANIFEST.in
README.rst
setup.py
json2xlsx/__init__.py
json2xlsx.egg-info/PKG-INFO
json2xlsx.egg-info/SOURCES.txt
json2xlsx.egg-info/dependency_links.txt
json2xlsx.egg-info/entry_points.txt
json2xlsx.egg-info/requires.txt
json2xlsx.egg-info/top_level.txt
json2xlsx.egg-info/zip-safe
json2xlsx/utilities/__init__.py
json2xlsx/utilities/json2xlsx.py