Metadata-Version: 1.1
Name: json2xlsx
Version: 1.2.5
Summary: Tool to generate xlsx (Excel spreadsheet) from JSON
Home-page: http://github.com/mkasa/json2xlsx
Author: Masahiro Kasahara
Author-email: mkasa@cb.k.u-tokyo.ac.jp
License: BSD
Platform: UNKNOWN
Classifier: Development Status :: 4 - Beta
Classifier: Environment :: Console
Classifier: Intended Audience :: Developers
Classifier: Intended Audience :: End Users/Desktop
Classifier: Intended Audience :: Science/Research
Classifier: License :: OSI Approved :: BSD License
Classifier: Natural Language :: English
Classifier: Operating System :: OS Independent
Classifier: Programming Language :: Python
Classifier: Programming Language :: Python :: 2.7
Classifier: Topic :: Scientific/Engineering :: Information Analysis
Classifier: Topic :: Software Development :: Libraries :: Python Modules
Classifier: Topic :: Utilities
